<?xml version="1.0" encoding="utf-8" ?>
<c2layout>
    <name>Layout 1</name>
    <sid>4650502934421703</sid>
    <event-sheet>Global Event sheet</event-sheet>
    <size>
        <width>1280</width>
        <height>1024</height>
    </size>
    <margins>
        <horizontal>500</horizontal>
        <vertical>500</vertical>
    </margins>
    <unbounded-scrolling>0</unbounded-scrolling>
    <layers>
        <layer name="Background" sid="6199299691916345">
            <initially-visible>1</initially-visible>
            <background-color>255,255,255</background-color>
            <transparent>0</transparent>
            <parallax>
                <x>1</x>
                <y>1</y>
            </parallax>
            <zoom-rate>1</zoom-rate>
            <opacity>1</opacity>
            <force-own-texture>0</force-own-texture>
            <global>0</global>
            <use-render-cells>0</use-render-cells>
            <blend-mode>0</blend-mode>
            <effect-fallback>0</effect-fallback>
            <instances>
                <instance type="BackgroundCave" uid="0">
                    <properties>
                        <initial-visibility>Visible</initial-visibility>
                        <initial-animation>Default</initial-animation>
                        <initial-frame>0</initial-frame>
                        <collisions>Enabled</collisions>
                    </properties>
                    <blend-mode>0</blend-mode>
                    <effect-fallback>0</effect-fallback>
                    <world>
                        <x>640</x>
                        <y>360</y>
                        <z>0</z>
                        <width>1280</width>
                        <height>720</height>
                        <depth>0</depth>
                        <hotspotX>0.5</hotspotX>
                        <hotspotY>0.5</hotspotY>
                        <angle>0</angle>
                        <opacity>1</opacity>
                    </world>
                </instance>
                <instance type="UiBackground" uid="13">
                    <properties>
                        <left-margin>16</left-margin>
                        <right-margin>16</right-margin>
                        <top-margin>16</top-margin>
                        <bottom-margin>16</bottom-margin>
                        <edges>Stretch</edges>
                        <fill>Stretch</fill>
                        <initial-visibility>Visible</initial-visibility>
                        <hotspot>Bottom-left</hotspot>
                        <seams>Overlap</seams>
                    </properties>
                    <blend-mode>0</blend-mode>
                    <effect-fallback>0</effect-fallback>
                    <world>
                        <x>0</x>
                        <y>1024</y>
                        <z>0</z>
                        <width>1280</width>
                        <height>325</height>
                        <depth>0</depth>
                        <hotspotX>0</hotspotX>
                        <hotspotY>1</hotspotY>
                        <opacity>1</opacity>
                    </world>
                </instance>
                <instance type="CurrencyBackground" uid="14">
                    <properties>
                        <left-margin>16</left-margin>
                        <right-margin>16</right-margin>
                        <top-margin>16</top-margin>
                        <bottom-margin>16</bottom-margin>
                        <edges>Stretch</edges>
                        <fill>Stretch</fill>
                        <initial-visibility>Visible</initial-visibility>
                        <hotspot>Top-left</hotspot>
                        <seams>Overlap</seams>
                    </properties>
                    <blend-mode>0</blend-mode>
                    <effect-fallback>0</effect-fallback>
                    <world>
                        <x>1043</x>
                        <y>712</y>
                        <z>0</z>
                        <width>226</width>
                        <height>302</height>
                        <depth>0</depth>
                        <hotspotX>0</hotspotX>
                        <hotspotY>0</hotspotY>
                        <opacity>1</opacity>
                    </world>
                </instance>
            </instances>
            <effects />
        </layer>
        <layer name="Interface" sid="800021564812611">
            <initially-visible>1</initially-visible>
            <background-color>255,255,255</background-color>
            <transparent>1</transparent>
            <parallax>
                <x>1</x>
                <y>1</y>
            </parallax>
            <zoom-rate>1</zoom-rate>
            <opacity>1</opacity>
            <force-own-texture>0</force-own-texture>
            <global>0</global>
            <use-render-cells>0</use-render-cells>
            <blend-mode>0</blend-mode>
            <effect-fallback>0</effect-fallback>
            <instances>
                <instance type="Slimebud" uid="2">
                    <properties>
                        <initial-visibility>Visible</initial-visibility>
                        <initial-animation>Default</initial-animation>
                        <initial-frame>0</initial-frame>
                        <collisions>Enabled</collisions>
                    </properties>
                    <instance-variables>
                        <GreenSlime>11200000000</GreenSlime>
                        <GScaleMod>1</GScaleMod>
                        <CGGValue>0</CGGValue>
                        <PGGValue>0.1</PGGValue>
                        <RedSlime>1000000000000</RedSlime>
                        <RScaleMod>1</RScaleMod>
                        <RGDropRate>0</RGDropRate>
                        <CRGValue>1</CRGValue>
                        <PRGValue>0</PRGValue>
                        <SlimeLeftOver>0</SlimeLeftOver>
                        <GreenLoseOnRed>0.01</GreenLoseOnRed>
                        <NBGperSecond>1</NBGperSecond>
                        <CGGMultiplicator>1</CGGMultiplicator>
                        <PGGMultiplicator>1</PGGMultiplicator>
                        <PRGMultiplicator>1</PRGMultiplicator>
                        <CRGMultiplicator>1</CRGMultiplicator>
                        <PGGBase>0</PGGBase>
                        <CGGBase>1</CGGBase>
                        <PRGBase>1</PRGBase>
                        <CRGBase>1</CRGBase>
                    </instance-variables>
                    <blend-mode>0</blend-mode>
                    <effect-fallback>0</effect-fallback>
                    <world>
                        <x>650</x>
                        <y>667</y>
                        <z>0</z>
                        <width>179.469100952</width>
                        <height>179.469100952</height>
                        <depth>0</depth>
                        <hotspotX>0.5</hotspotX>
                        <hotspotY>0.954545438</hotspotY>
                        <angle>0</angle>
                        <opacity>1</opacity>
                    </world>
                </instance>
                <instance type="Tank" uid="8">
                    <properties>
                        <initial-visibility>Visible</initial-visibility>
                        <initial-animation>Default</initial-animation>
                        <initial-frame>0</initial-frame>
                        <collisions>Enabled</collisions>
                    </properties>
                    <blend-mode>0</blend-mode>
                    <effect-fallback>0</effect-fallback>
                    <world>
                        <x>640</x>
                        <y>0</y>
                        <z>0</z>
                        <width>1280</width>
                        <height>400</height>
                        <depth>0</depth>
                        <hotspotX>0.5</hotspotX>
                        <hotspotY>0.5</hotspotY>
                        <angle>0</angle>
                        <opacity>1</opacity>
                    </world>
                </instance>
                <instance type="CGreenGoutte" uid="9">
                    <properties>
                        <initial-visibility>Visible</initial-visibility>
                        <initial-animation>Default</initial-animation>
                        <initial-frame>0</initial-frame>
                        <collisions>Enabled</collisions>
                    </properties>
                    <behavior-instances>
                        <behavior-instance type="Physics">
                            <properties>
                                <immovable>No</immovable>
                                <collision-mask>Circle</collision-mask>
                                <prevent-rotation>Yes</prevent-rotation>
                                <density>1</density>
                                <friction>0.5</friction>
                                <elasticity>0.2</elasticity>
                                <linear-damping>0</linear-damping>
                                <angular-damping>0.01</angular-damping>
                                <bullet>No</bullet>
                                <initial-state>Enabled</initial-state>
                            </properties>
                        </behavior-instance>
                    </behavior-instances>
                    <blend-mode>0</blend-mode>
                    <effect-fallback>0</effect-fallback>
                    <world>
                        <x>1431</x>
                        <y>265</y>
                        <z>0</z>
                        <width>64</width>
                        <height>41</height>
                        <depth>0</depth>
                        <hotspotX>0.5</hotspotX>
                        <hotspotY>0.51219511</hotspotY>
                        <angle>0</angle>
                        <opacity>1</opacity>
                    </world>
                </instance>
                <instance type="TotalGS_Icon" uid="10">
                    <properties>
                        <initial-visibility>Visible</initial-visibility>
                        <initial-animation>Default</initial-animation>
                        <initial-frame>0</initial-frame>
                        <collisions>Enabled</collisions>
                    </properties>
                    <blend-mode>0</blend-mode>
                    <effect-fallback>0</effect-fallback>
                    <world>
                        <x>1080</x>
                        <y>750</y>
                        <z>0</z>
                        <width>35</width>
                        <height>35</height>
                        <depth>0</depth>
                        <hotspotX>0.5</hotspotX>
                        <hotspotY>0.5</hotspotY>
                        <angle>0</angle>
                        <opacity>1</opacity>
                    </world>
                </instance>
                <instance type="TotalGS_Value" uid="11">
                    <properties>
                        <text>Text</text>
                        <initial-visibility>Visible</initial-visibility>
                        <font>Retro Gaming,-32,400,0</font>
                        <color>0,204,0</color>
                        <horizontal-alignment>Left</horizontal-alignment>
                        <vertical-alignment>Center</vertical-alignment>
                        <hotspot>Left</hotspot>
                        <wrapping>Word</wrapping>
                        <line-height>0</line-height>
                    </properties>
                    <blend-mode>0</blend-mode>
                    <effect-fallback>0</effect-fallback>
                    <world>
                        <x>1100</x>
                        <y>752</y>
                        <z>0</z>
                        <width>162</width>
                        <height>50</height>
                        <depth>0</depth>
                        <hotspotX>0</hotspotX>
                        <hotspotY>0.5</hotspotY>
                        <angle>0</angle>
                        <opacity>1</opacity>
                    </world>
                </instance>
                <instance type="GGGain" uid="12">
                    <properties>
                        <text>Text</text>
                        <initial-visibility>Visible</initial-visibility>
                        <font>Retro Gaming,-26.4,700,0</font>
                        <color>0,204,0</color>
                        <horizontal-alignment>Center</horizontal-alignment>
                        <vertical-alignment>Center</vertical-alignment>
                        <hotspot>Bottom</hotspot>
                        <wrapping>Word</wrapping>
                        <line-height>0</line-height>
                    </properties>
                    <behavior-instances>
                        <behavior-instance type="Physics">
                            <properties>
                                <immovable>No</immovable>
                                <collision-mask>Circle</collision-mask>
                                <prevent-rotation>Yes</prevent-rotation>
                                <density>0</density>
                                <friction>0.5</friction>
                                <elasticity>0.2</elasticity>
                                <linear-damping>1</linear-damping>
                                <angular-damping>0.01</angular-damping>
                                <bullet>No</bullet>
                                <initial-state>Enabled</initial-state>
                            </properties>
                        </behavior-instance>
                        <behavior-instance type="Fade">
                            <properties>
                                <active-at-start>Yes</active-at-start>
                                <fade-in-time>0</fade-in-time>
                                <wait-time>0</wait-time>
                                <fade-out-time>1</fade-out-time>
                                <destroy>After fade out</destroy>
                            </properties>
                        </behavior-instance>
                    </behavior-instances>
                    <blend-mode>0</blend-mode>
                    <effect-fallback>0</effect-fallback>
                    <world>
                        <x>1426</x>
                        <y>463</y>
                        <z>0</z>
                        <width>200</width>
                        <height>50</height>
                        <depth>0</depth>
                        <hotspotX>0.5</hotspotX>
                        <hotspotY>1</hotspotY>
                        <angle>0</angle>
                        <opacity>1</opacity>
                    </world>
                </instance>
                <instance type="TankTab" uid="15">
                    <properties>
                        <initial-visibility>Visible</initial-visibility>
                        <initial-animation>Default</initial-animation>
                        <initial-frame>0</initial-frame>
                        <collisions>Enabled</collisions>
                    </properties>
                    <blend-mode>0</blend-mode>
                    <effect-fallback>0</effect-fallback>
                    <world>
                        <x>124</x>
                        <y>736</y>
                        <z>0</z>
                        <width>190</width>
                        <height>49</height>
                        <depth>0</depth>
                        <hotspotX>0.5</hotspotX>
                        <hotspotY>0.510204077</hotspotY>
                        <angle>0</angle>
                        <opacity>1</opacity>
                    </world>
                </instance>
                <instance type="TankTab_Text" uid="16">
                    <properties>
                        <text>Tank</text>
                        <initial-visibility>Visible</initial-visibility>
                        <font>Retro Gaming,-21.6,400,0</font>
                        <color>0,0,0</color>
                        <horizontal-alignment>Left</horizontal-alignment>
                        <vertical-alignment>Center</vertical-alignment>
                        <hotspot>Top-left</hotspot>
                        <wrapping>Word</wrapping>
                        <line-height>0</line-height>
                    </properties>
                    <blend-mode>0</blend-mode>
                    <effect-fallback>0</effect-fallback>
                    <world>
                        <x>45</x>
                        <y>720</y>
                        <z>0</z>
                        <width>127</width>
                        <height>30</height>
                        <depth>0</depth>
                        <hotspotX>0</hotspotX>
                        <hotspotY>0</hotspotY>
                        <angle>0</angle>
                        <opacity>1</opacity>
                    </world>
                </instance>
                <instance type="BudTab" uid="17">
                    <properties>
                        <initial-visibility>Visible</initial-visibility>
                        <initial-animation>Default</initial-animation>
                        <initial-frame>0</initial-frame>
                        <collisions>Enabled</collisions>
                    </properties>
                    <blend-mode>0</blend-mode>
                    <effect-fallback>0</effect-fallback>
                    <world>
                        <x>316</x>
                        <y>737</y>
                        <z>0</z>
                        <width>190</width>
                        <height>49</height>
                        <depth>0</depth>
                        <hotspotX>0.5</hotspotX>
                        <hotspotY>0.510204077</hotspotY>
                        <angle>0</angle>
                        <opacity>1</opacity>
                    </world>
                </instance>
                <instance type="BudTab_Text" uid="18">
                    <properties>
                        <text>Buddy</text>
                        <initial-visibility>Visible</initial-visibility>
                        <font>Retro Gaming,-21.6,400,0</font>
                        <color>0,0,0</color>
                        <horizontal-alignment>Left</horizontal-alignment>
                        <vertical-alignment>Center</vertical-alignment>
                        <hotspot>Top-left</hotspot>
                        <wrapping>Word</wrapping>
                        <line-height>0</line-height>
                    </properties>
                    <blend-mode>0</blend-mode>
                    <effect-fallback>0</effect-fallback>
                    <world>
                        <x>231</x>
                        <y>719</y>
                        <z>0</z>
                        <width>127</width>
                        <height>30</height>
                        <depth>0</depth>
                        <hotspotX>0</hotspotX>
                        <hotspotY>0</hotspotY>
                        <angle>0</angle>
                        <opacity>1</opacity>
                    </world>
                </instance>
                <instance type="ButtonBackground" uid="19">
                    <properties>
                        <left-margin>16</left-margin>
                        <right-margin>16</right-margin>
                        <top-margin>16</top-margin>
                        <bottom-margin>16</bottom-margin>
                        <edges>Stretch</edges>
                        <fill>Stretch</fill>
                        <initial-visibility>Visible</initial-visibility>
                        <hotspot>Top-left</hotspot>
                        <seams>Overlap</seams>
                    </properties>
                    <blend-mode>0</blend-mode>
                    <effect-fallback>0</effect-fallback>
                    <world>
                        <x>10</x>
                        <y>750</y>
                        <z>0</z>
                        <width>1020</width>
                        <height>265</height>
                        <depth>0</depth>
                        <hotspotX>0</hotspotX>
                        <hotspotY>0</hotspotY>
                        <opacity>1</opacity>
                    </world>
                </instance>
                <instance type="Buttons" uid="20">
                    <properties>
                        <initial-visibility>Visible</initial-visibility>
                        <initial-animation>Default</initial-animation>
                        <initial-frame>0</initial-frame>
                        <collisions>Enabled</collisions>
                    </properties>
                    <instance-variables>
                        <Cost>0</Cost>
                        <ErosionLevel>0</ErosionLevel>
                        <MaxLevel>100</MaxLevel>
                    </instance-variables>
                    <blend-mode>0</blend-mode>
                    <effect-fallback>0</effect-fallback>
                    <world>
                        <x>20</x>
                        <y>760</y>
                        <z>0</z>
                        <width>500</width>
                        <height>115</height>
                        <depth>0</depth>
                        <hotspotX>0</hotspotX>
                        <hotspotY>0</hotspotY>
                        <angle>0</angle>
                        <opacity>1</opacity>
                    </world>
                </instance>
                <instance type="Buttons2" uid="21">
                    <properties>
                        <initial-visibility>Visible</initial-visibility>
                        <initial-animation>Default</initial-animation>
                        <initial-frame>0</initial-frame>
                        <collisions>Enabled</collisions>
                    </properties>
                    <instance-variables>
                        <Cost>0</Cost>
                        <Level>0</Level>
                    </instance-variables>
                    <blend-mode>0</blend-mode>
                    <effect-fallback>0</effect-fallback>
                    <world>
                        <x>1022</x>
                        <y>760</y>
                        <z>0</z>
                        <width>500</width>
                        <height>115</height>
                        <depth>0</depth>
                        <hotspotX>1</hotspotX>
                        <hotspotY>0</hotspotY>
                        <angle>0</angle>
                        <opacity>1</opacity>
                    </world>
                </instance>
                <instance type="Buttons3" uid="22">
                    <properties>
                        <initial-visibility>Visible</initial-visibility>
                        <initial-animation>Default</initial-animation>
                        <initial-frame>0</initial-frame>
                        <collisions>Enabled</collisions>
                    </properties>
                    <blend-mode>0</blend-mode>
                    <effect-fallback>0</effect-fallback>
                    <world>
                        <x>20</x>
                        <y>1000</y>
                        <z>0</z>
                        <width>500</width>
                        <height>115</height>
                        <depth>0</depth>
                        <hotspotX>0</hotspotX>
                        <hotspotY>1.020408154</hotspotY>
                        <angle>0</angle>
                        <opacity>1</opacity>
                    </world>
                </instance>
                <instance type="Buttons4" uid="23">
                    <properties>
                        <initial-visibility>Visible</initial-visibility>
                        <initial-animation>Default</initial-animation>
                        <initial-frame>0</initial-frame>
                        <collisions>Enabled</collisions>
                    </properties>
                    <blend-mode>0</blend-mode>
                    <effect-fallback>0</effect-fallback>
                    <world>
                        <x>1022</x>
                        <y>1000</y>
                        <z>0</z>
                        <width>500</width>
                        <height>115</height>
                        <depth>0</depth>
                        <hotspotX>1</hotspotX>
                        <hotspotY>1.020408154</hotspotY>
                        <angle>0</angle>
                        <opacity>1</opacity>
                    </world>
                </instance>
                <instance type="TButton1_Name" uid="25">
                    <properties>
                        <text>EROSION</text>
                        <initial-visibility>Visible</initial-visibility>
                        <font>Retro Gaming,-21.6,400,0</font>
                        <color>0,0,0</color>
                        <horizontal-alignment>Left</horizontal-alignment>
                        <vertical-alignment>Top</vertical-alignment>
                        <hotspot>Top-left</hotspot>
                        <wrapping>Word</wrapping>
                        <line-height>0</line-height>
                    </properties>
                    <blend-mode>0</blend-mode>
                    <effect-fallback>0</effect-fallback>
                    <world>
                        <x>134</x>
                        <y>772</y>
                        <z>0</z>
                        <width>271</width>
                        <height>29</height>
                        <depth>0</depth>
                        <hotspotX>0</hotspotX>
                        <hotspotY>0</hotspotY>
                        <angle>0</angle>
                        <opacity>1</opacity>
                    </world>
                </instance>
                <instance type="TButton1_Description" uid="26">
                    <properties>
                        <text>+0.1 to passive slime drop value.</text>
                        <initial-visibility>Visible</initial-visibility>
                        <font>Retro Gaming,-16,400,0</font>
                        <color>0,0,0</color>
                        <horizontal-alignment>Left</horizontal-alignment>
                        <vertical-alignment>Top</vertical-alignment>
                        <hotspot>Top-left</hotspot>
                        <wrapping>Word</wrapping>
                        <line-height>0</line-height>
                    </properties>
                    <blend-mode>0</blend-mode>
                    <effect-fallback>0</effect-fallback>
                    <world>
                        <x>136</x>
                        <y>800</y>
                        <z>0</z>
                        <width>373</width>
                        <height>77</height>
                        <depth>0</depth>
                        <hotspotX>0</hotspotX>
                        <hotspotY>0</hotspotY>
                        <angle>0</angle>
                        <opacity>1</opacity>
                    </world>
                </instance>
                <instance type="TButton1_Cost" uid="27">
                    <properties>
                        <text>Text</text>
                        <initial-visibility>Visible</initial-visibility>
                        <font>Retro Gaming,-16,700,0</font>
                        <color>0,0,0</color>
                        <horizontal-alignment>Right</horizontal-alignment>
                        <vertical-alignment>Top</vertical-alignment>
                        <hotspot>Top-left</hotspot>
                        <wrapping>Word</wrapping>
                        <line-height>0</line-height>
                    </properties>
                    <blend-mode>0</blend-mode>
                    <effect-fallback>0</effect-fallback>
                    <world>
                        <x>304</x>
                        <y>773</y>
                        <z>0</z>
                        <width>192</width>
                        <height>24</height>
                        <depth>0</depth>
                        <hotspotX>0</hotspotX>
                        <hotspotY>0</hotspotY>
                        <angle>0</angle>
                        <opacity>1</opacity>
                    </world>
                </instance>
                <instance type="TotalRS_Icon" uid="28">
                    <properties>
                        <initial-visibility>Invisible</initial-visibility>
                        <initial-animation>Default</initial-animation>
                        <initial-frame>0</initial-frame>
                        <collisions>Enabled</collisions>
                    </properties>
                    <blend-mode>0</blend-mode>
                    <effect-fallback>0</effect-fallback>
                    <world>
                        <x>1080</x>
                        <y>840</y>
                        <z>0</z>
                        <width>35</width>
                        <height>35</height>
                        <depth>0</depth>
                        <hotspotX>0.5</hotspotX>
                        <hotspotY>0.5</hotspotY>
                        <angle>0</angle>
                        <opacity>1</opacity>
                    </world>
                </instance>
                <instance type="TotalRS_Value" uid="29">
                    <properties>
                        <text>Text</text>
                        <initial-visibility>Invisible</initial-visibility>
                        <font>Retro Gaming,-32,700,0</font>
                        <color>255,51,0</color>
                        <horizontal-alignment>Left</horizontal-alignment>
                        <vertical-alignment>Center</vertical-alignment>
                        <hotspot>Left</hotspot>
                        <wrapping>Word</wrapping>
                        <line-height>0</line-height>
                    </properties>
                    <blend-mode>0</blend-mode>
                    <effect-fallback>0</effect-fallback>
                    <world>
                        <x>1100</x>
                        <y>840</y>
                        <z>0</z>
                        <width>162</width>
                        <height>50</height>
                        <depth>0</depth>
                        <hotspotX>0</hotspotX>
                        <hotspotY>0.5</hotspotY>
                        <angle>0</angle>
                        <opacity>1</opacity>
                    </world>
                </instance>
                <instance type="GSpC_Value" uid="30">
                    <properties>
                        <text>Text</text>
                        <initial-visibility>Visible</initial-visibility>
                        <font>Retro Gaming,-32,700,0</font>
                        <color>0,204,0</color>
                        <horizontal-alignment>Left</horizontal-alignment>
                        <vertical-alignment>Center</vertical-alignment>
                        <hotspot>Left</hotspot>
                        <wrapping>Word</wrapping>
                        <line-height>0</line-height>
                    </properties>
                    <blend-mode>0</blend-mode>
                    <effect-fallback>0</effect-fallback>
                    <world>
                        <x>1100</x>
                        <y>790</y>
                        <z>0</z>
                        <width>164</width>
                        <height>54</height>
                        <depth>0</depth>
                        <hotspotX>0</hotspotX>
                        <hotspotY>0.5</hotspotY>
                        <angle>0</angle>
                        <opacity>1</opacity>
                    </world>
                </instance>
                <instance type="RSpC_Value" uid="31">
                    <properties>
                        <text>Text</text>
                        <initial-visibility>Invisible</initial-visibility>
                        <font>Retro Gaming,-32,700,0</font>
                        <color>255,51,0</color>
                        <horizontal-alignment>Left</horizontal-alignment>
                        <vertical-alignment>Center</vertical-alignment>
                        <hotspot>Left</hotspot>
                        <wrapping>Word</wrapping>
                        <line-height>0</line-height>
                    </properties>
                    <blend-mode>0</blend-mode>
                    <effect-fallback>0</effect-fallback>
                    <world>
                        <x>1100</x>
                        <y>880</y>
                        <z>0</z>
                        <width>162</width>
                        <height>54</height>
                        <depth>0</depth>
                        <hotspotX>0</hotspotX>
                        <hotspotY>0.5</hotspotY>
                        <angle>0</angle>
                        <opacity>1</opacity>
                    </world>
                </instance>
                <instance type="Sprite2" uid="32">
                    <properties>
                        <initial-visibility>Visible</initial-visibility>
                        <initial-animation>Default</initial-animation>
                        <initial-frame>0</initial-frame>
                        <collisions>Enabled</collisions>
                    </properties>
                    <blend-mode>0</blend-mode>
                    <effect-fallback>0</effect-fallback>
                    <world>
                        <x>1080</x>
                        <y>790</y>
                        <z>0</z>
                        <width>32</width>
                        <height>40</height>
                        <depth>0</depth>
                        <hotspotX>0.5</hotspotX>
                        <hotspotY>0.470588237</hotspotY>
                        <angle>0</angle>
                        <opacity>1</opacity>
                    </world>
                </instance>
                <instance type="Sprite3" uid="33">
                    <properties>
                        <initial-visibility>Invisible</initial-visibility>
                        <initial-animation>Default</initial-animation>
                        <initial-frame>0</initial-frame>
                        <collisions>Enabled</collisions>
                    </properties>
                    <blend-mode>0</blend-mode>
                    <effect-fallback>0</effect-fallback>
                    <world>
                        <x>1080</x>
                        <y>880</y>
                        <z>0</z>
                        <width>32</width>
                        <height>40</height>
                        <depth>0</depth>
                        <hotspotX>0.5</hotspotX>
                        <hotspotY>0.529411793</hotspotY>
                        <angle>0</angle>
                        <opacity>1</opacity>
                    </world>
                </instance>
                <instance type="TButton2_Name" uid="34">
                    <properties>
                        <text>INOFFENSIVE</text>
                        <initial-visibility>Invisible</initial-visibility>
                        <font>Retro Gaming,-23,400,0</font>
                        <color>0,0,0</color>
                        <horizontal-alignment>Left</horizontal-alignment>
                        <vertical-alignment>Top</vertical-alignment>
                        <hotspot>Top-left</hotspot>
                        <wrapping>Word</wrapping>
                        <line-height>0</line-height>
                    </properties>
                    <blend-mode>0</blend-mode>
                    <effect-fallback>0</effect-fallback>
                    <world>
                        <x>638</x>
                        <y>772</y>
                        <z>0</z>
                        <width>327</width>
                        <height>32</height>
                        <depth>0</depth>
                        <hotspotX>0</hotspotX>
                        <hotspotY>0</hotspotY>
                        <angle>0</angle>
                        <opacity>1</opacity>
                    </world>
                </instance>
                <instance type="TButton2_Cost" uid="35">
                    <properties>
                        <text>Text</text>
                        <initial-visibility>Invisible</initial-visibility>
                        <font>Retro Gaming,-16,400,0</font>
                        <color>0,0,0</color>
                        <horizontal-alignment>Right</horizontal-alignment>
                        <vertical-alignment>Top</vertical-alignment>
                        <hotspot>Top-left</hotspot>
                        <wrapping>Word</wrapping>
                        <line-height>0</line-height>
                    </properties>
                    <blend-mode>0</blend-mode>
                    <effect-fallback>0</effect-fallback>
                    <world>
                        <x>810</x>
                        <y>773</y>
                        <z>0</z>
                        <width>192</width>
                        <height>24</height>
                        <depth>0</depth>
                        <hotspotX>0</hotspotX>
                        <hotspotY>0</hotspotY>
                        <angle>0</angle>
                        <opacity>1</opacity>
                    </world>
                </instance>
                <instance type="TButton2_Description" uid="36">
                    <properties>
                        <text>Increases value of red goo drops to 110%. Reduces value of slime drops to 95%.</text>
                        <initial-visibility>Invisible</initial-visibility>
                        <font>Retro Gaming,-16,400,0</font>
                        <color>0,0,0</color>
                        <horizontal-alignment>Left</horizontal-alignment>
                        <vertical-alignment>Top</vertical-alignment>
                        <hotspot>Top-left</hotspot>
                        <wrapping>Word</wrapping>
                        <line-height>0</line-height>
                    </properties>
                    <blend-mode>0</blend-mode>
                    <effect-fallback>0</effect-fallback>
                    <world>
                        <x>638</x>
                        <y>800</y>
                        <z>0</z>
                        <width>373</width>
                        <height>71</height>
                        <depth>0</depth>
                        <hotspotX>0</hotspotX>
                        <hotspotY>0</hotspotY>
                        <angle>0</angle>
                        <opacity>1</opacity>
                    </world>
                </instance>
                <instance type="CRedGoutte" uid="37">
                    <properties>
                        <initial-visibility>Visible</initial-visibility>
                        <initial-animation>Default</initial-animation>
                        <initial-frame>0</initial-frame>
                        <collisions>Enabled</collisions>
                    </properties>
                    <behavior-instances>
                        <behavior-instance type="Physics">
                            <properties>
                                <immovable>No</immovable>
                                <collision-mask>Circle</collision-mask>
                                <prevent-rotation>Yes</prevent-rotation>
                                <density>1</density>
                                <friction>0.5</friction>
                                <elasticity>0.2</elasticity>
                                <linear-damping>0</linear-damping>
                                <angular-damping>0.01</angular-damping>
                                <bullet>No</bullet>
                                <initial-state>Enabled</initial-state>
                            </properties>
                        </behavior-instance>
                    </behavior-instances>
                    <blend-mode>0</blend-mode>
                    <effect-fallback>0</effect-fallback>
                    <world>
                        <x>1502</x>
                        <y>325</y>
                        <z>0</z>
                        <width>64</width>
                        <height>41</height>
                        <depth>0</depth>
                        <hotspotX>0.5</hotspotX>
                        <hotspotY>0.51219511</hotspotY>
                        <angle>0</angle>
                        <opacity>1</opacity>
                    </world>
                </instance>
                <instance type="TotalGS_Icon" uid="39">
                    <properties>
                        <initial-visibility>Visible</initial-visibility>
                        <initial-animation>Default</initial-animation>
                        <initial-frame>0</initial-frame>
                        <collisions>Enabled</collisions>
                    </properties>
                    <blend-mode>0</blend-mode>
                    <effect-fallback>0</effect-fallback>
                    <world>
                        <x>507</x>
                        <y>782</y>
                        <z>0</z>
                        <width>19</width>
                        <height>19</height>
                        <depth>0</depth>
                        <hotspotX>0.5</hotspotX>
                        <hotspotY>0.5</hotspotY>
                        <angle>0</angle>
                        <opacity>1</opacity>
                    </world>
                </instance>
                <instance type="RS_Cost_Icon" uid="40">
                    <properties>
                        <initial-visibility>Invisible</initial-visibility>
                        <initial-animation>Default</initial-animation>
                        <initial-frame>0</initial-frame>
                        <collisions>Enabled</collisions>
                    </properties>
                    <blend-mode>0</blend-mode>
                    <effect-fallback>0</effect-fallback>
                    <world>
                        <x>1010</x>
                        <y>782</y>
                        <z>0</z>
                        <width>16</width>
                        <height>16</height>
                        <depth>0</depth>
                        <hotspotX>0.5</hotspotX>
                        <hotspotY>0.5</hotspotY>
                        <angle>0</angle>
                        <opacity>1</opacity>
                    </world>
                </instance>
                <instance type="TButton1Level" uid="47">
                    <properties>
                        <text>Text</text>
                        <initial-visibility>Visible</initial-visibility>
                        <font>Retro Gaming,-13,400,0</font>
                        <color>0,0,0</color>
                        <horizontal-alignment>Right</horizontal-alignment>
                        <vertical-alignment>Top</vertical-alignment>
                        <hotspot>Top-left</hotspot>
                        <wrapping>Word</wrapping>
                        <line-height>0</line-height>
                    </properties>
                    <blend-mode>0</blend-mode>
                    <effect-fallback>0</effect-fallback>
                    <world>
                        <x>356</x>
                        <y>838</y>
                        <z>0</z>
                        <width>153</width>
                        <height>26</height>
                        <depth>0</depth>
                        <hotspotX>0</hotspotX>
                        <hotspotY>0</hotspotY>
                        <angle>0</angle>
                        <opacity>1</opacity>
                    </world>
                </instance>
            </instances>
            <effects />
        </layer>
        <layer name="BuddyButtons" sid="564462272788854">
            <initially-visible>0</initially-visible>
            <background-color>255,255,255</background-color>
            <transparent>1</transparent>
            <parallax>
                <x>1</x>
                <y>1</y>
            </parallax>
            <zoom-rate>1</zoom-rate>
            <opacity>1</opacity>
            <force-own-texture>0</force-own-texture>
            <global>0</global>
            <use-render-cells>0</use-render-cells>
            <blend-mode>0</blend-mode>
            <effect-fallback>0</effect-fallback>
            <instances>
                <instance type="ButtonBackground" uid="24">
                    <properties>
                        <left-margin>16</left-margin>
                        <right-margin>16</right-margin>
                        <top-margin>16</top-margin>
                        <bottom-margin>16</bottom-margin>
                        <edges>Stretch</edges>
                        <fill>Stretch</fill>
                        <initial-visibility>Visible</initial-visibility>
                        <hotspot>Top-left</hotspot>
                        <seams>Overlap</seams>
                    </properties>
                    <blend-mode>0</blend-mode>
                    <effect-fallback>0</effect-fallback>
                    <world>
                        <x>10</x>
                        <y>750</y>
                        <z>0</z>
                        <width>1020</width>
                        <height>265</height>
                        <depth>0</depth>
                        <hotspotX>0</hotspotX>
                        <hotspotY>0</hotspotY>
                        <opacity>1</opacity>
                    </world>
                </instance>
                <instance type="Button11" uid="1">
                    <properties>
                        <initial-visibility>Visible</initial-visibility>
                        <initial-animation>Default</initial-animation>
                        <initial-frame>0</initial-frame>
                        <collisions>Enabled</collisions>
                    </properties>
                    <instance-variables>
                        <Cost>10</Cost>
                        <Level>0</Level>
                        <MaxLevel>10</MaxLevel>
                    </instance-variables>
                    <blend-mode>0</blend-mode>
                    <effect-fallback>0</effect-fallback>
                    <world>
                        <x>20</x>
                        <y>760</y>
                        <z>0</z>
                        <width>500</width>
                        <height>115</height>
                        <depth>0</depth>
                        <hotspotX>0</hotspotX>
                        <hotspotY>0</hotspotY>
                        <angle>0</angle>
                        <opacity>1</opacity>
                    </world>
                </instance>
                <instance type="Button12" uid="41">
                    <properties>
                        <initial-visibility>Visible</initial-visibility>
                        <initial-animation>Default</initial-animation>
                        <initial-frame>0</initial-frame>
                        <collisions>Enabled</collisions>
                    </properties>
                    <blend-mode>0</blend-mode>
                    <effect-fallback>0</effect-fallback>
                    <world>
                        <x>1022</x>
                        <y>760</y>
                        <z>0</z>
                        <width>500</width>
                        <height>115</height>
                        <depth>0</depth>
                        <hotspotX>1</hotspotX>
                        <hotspotY>0</hotspotY>
                        <angle>0</angle>
                        <opacity>1</opacity>
                    </world>
                </instance>
                <instance type="Button13" uid="42">
                    <properties>
                        <initial-visibility>Visible</initial-visibility>
                        <initial-animation>Default</initial-animation>
                        <initial-frame>0</initial-frame>
                        <collisions>Enabled</collisions>
                    </properties>
                    <blend-mode>0</blend-mode>
                    <effect-fallback>0</effect-fallback>
                    <world>
                        <x>20</x>
                        <y>1000</y>
                        <z>0</z>
                        <width>500</width>
                        <height>115</height>
                        <depth>0</depth>
                        <hotspotX>0</hotspotX>
                        <hotspotY>1.020408154</hotspotY>
                        <angle>0</angle>
                        <opacity>1</opacity>
                    </world>
                </instance>
                <instance type="Button14" uid="43">
                    <properties>
                        <initial-visibility>Visible</initial-visibility>
                        <initial-animation>Default</initial-animation>
                        <initial-frame>0</initial-frame>
                        <collisions>Enabled</collisions>
                    </properties>
                    <blend-mode>0</blend-mode>
                    <effect-fallback>0</effect-fallback>
                    <world>
                        <x>1022</x>
                        <y>1000</y>
                        <z>0</z>
                        <width>500</width>
                        <height>115</height>
                        <depth>0</depth>
                        <hotspotX>1</hotspotX>
                        <hotspotY>1.020408154</hotspotY>
                        <angle>0</angle>
                        <opacity>1</opacity>
                    </world>
                </instance>
                <instance type="BButton11_Name" uid="44">
                    <properties>
                        <text>JUMP!</text>
                        <initial-visibility>Visible</initial-visibility>
                        <font>Retro Gaming,-22.4,400,0</font>
                        <color>0,0,0</color>
                        <horizontal-alignment>Left</horizontal-alignment>
                        <vertical-alignment>Top</vertical-alignment>
                        <hotspot>Top-left</hotspot>
                        <wrapping>Word</wrapping>
                        <line-height>0</line-height>
                    </properties>
                    <blend-mode>0</blend-mode>
                    <effect-fallback>0</effect-fallback>
                    <world>
                        <x>134</x>
                        <y>772</y>
                        <z>0</z>
                        <width>271</width>
                        <height>29</height>
                        <depth>0</depth>
                        <hotspotX>0</hotspotX>
                        <hotspotY>0</hotspotY>
                        <angle>0</angle>
                        <opacity>1</opacity>
                    </world>
                </instance>
                <instance type="BButton11_Description" uid="45">
                    <properties>
                        <text>+1 Slime/click</text>
                        <initial-visibility>Visible</initial-visibility>
                        <font>Retro Gaming,-16,400,0</font>
                        <color>0,0,0</color>
                        <horizontal-alignment>Left</horizontal-alignment>
                        <vertical-alignment>Top</vertical-alignment>
                        <hotspot>Top-left</hotspot>
                        <wrapping>Word</wrapping>
                        <line-height>0</line-height>
                    </properties>
                    <blend-mode>0</blend-mode>
                    <effect-fallback>0</effect-fallback>
                    <world>
                        <x>136</x>
                        <y>800</y>
                        <z>0</z>
                        <width>373</width>
                        <height>77</height>
                        <depth>0</depth>
                        <hotspotX>0</hotspotX>
                        <hotspotY>0</hotspotY>
                        <angle>0</angle>
                        <opacity>1</opacity>
                    </world>
                </instance>
                <instance type="BButton11_Cost" uid="46">
                    <properties>
                        <text>Button11.Cost</text>
                        <initial-visibility>Visible</initial-visibility>
                        <font>Retro Gaming,-16,400,0</font>
                        <color>0,0,0</color>
                        <horizontal-alignment>Right</horizontal-alignment>
                        <vertical-alignment>Top</vertical-alignment>
                        <hotspot>Top-left</hotspot>
                        <wrapping>Word</wrapping>
                        <line-height>0</line-height>
                    </properties>
                    <blend-mode>0</blend-mode>
                    <effect-fallback>0</effect-fallback>
                    <world>
                        <x>304</x>
                        <y>773</y>
                        <z>0</z>
                        <width>192</width>
                        <height>24</height>
                        <depth>0</depth>
                        <hotspotX>0</hotspotX>
                        <hotspotY>0</hotspotY>
                        <angle>0</angle>
                        <opacity>1</opacity>
                    </world>
                </instance>
            </instances>
            <effects />
        </layer>
        <layer name="MetaButtons" sid="210869617573016">
            <initially-visible>0</initially-visible>
            <background-color>255,255,255</background-color>
            <transparent>1</transparent>
            <parallax>
                <x>1</x>
                <y>1</y>
            </parallax>
            <zoom-rate>1</zoom-rate>
            <opacity>1</opacity>
            <force-own-texture>0</force-own-texture>
            <global>0</global>
            <use-render-cells>0</use-render-cells>
            <blend-mode>0</blend-mode>
            <effect-fallback>0</effect-fallback>
            <instances />
            <effects />
        </layer>
    </layers>
    <nonworld-instances />
    <effects />
</c2layout>
